musibatln/__init__.py
musibatln/justgood.py
musibatln/shahzi.py
musibatln-0.2.1.dist-info/LICENSE
musibatln-0.2.1.dist-info/METADATA
musibatln-0.2.1.dist-info/WHEEL
musibatln-0.2.1.dist-info/top_level.txt
musibatln-0.2.1.dist-info/RECORD
