Metadata-Version: 2.1
Name: musibatln
Version: 0.2.1
Summary: Team Musibat Bots
Home-page: https://bitbucket.org/shahzain83/musibat
Author: Shahzain Khan
Author-email: asifjamali83@hotmail.com
License: MIT
Project-URL: Bug Tracker, https://bitbucket.org/shahzain83/musibat/issues
License-File: LICENSE
Requires-Dist: requests
